chastesweep/__init__.py
chastesweep/parametersweep.py
chastesweep/templates/__init__.py
chastesweep/templates/batch.sge.sh
chastesweep/templates/batch.slurm.sh
chastesweep/templates/main.cpp
chastesweep/templates/runsimulation.py
chastesweep/test/__init__.py
chastesweep/test/test_parametersweep.py
chastesweep/test/test_pscan.py
chastesweep/util/__init__.py
chastesweep/util/pscan.py
chastesweep-0.7.data/scripts/chastesweep_genmain
chastesweep-0.7.dist-info/LICENSE
chastesweep-0.7.dist-info/METADATA
chastesweep-0.7.dist-info/WHEEL
chastesweep-0.7.dist-info/top_level.txt
chastesweep-0.7.dist-info/RECORD
