Metadata-Version: 2.1
Name: chastesweep
Version: 0.7
Summary: Parameter Sweeper for Chaste
Home-page: https://github.com/twinkarma/chastesweep
Author: Twin Karmakharm
Author-email: t.karmakharm@sheffield.ac.uk
License: UNKNOWN
Platform: UNKNOWN
Classifier: Programming Language :: Python :: 2
Classifier: License :: OSI Approved :: MIT License
Classifier: Operating System :: OS Independent
Requires-Dist: numpy
Requires-Dist: jinja2
